create_readme/__init__.py
create_readme/generator.py
create_readme/multiline_input.py
create_readme/prompts.py
create_readme/run.py
create_readme-0.1.1.dist-info/METADATA
create_readme-0.1.1.dist-info/WHEEL
create_readme-0.1.1.dist-info/entry_points.txt
create_readme-0.1.1.dist-info/RECORD
