Metadata-Version: 2.1
Name: create-readme
Version: 0.1.1
Summary: 
Author: rizerphe
Author-email: 44440399+rizerphe@users.noreply.github.com
Requires-Python: >=3.11,<4.0
Classifier: Programming Language :: Python :: 3
Classifier: Programming Language :: Python :: 3.11
Requires-Dist: click (>=8.1.3,<9.0.0)
Requires-Dist: openai (>=0.27.8,<0.28.0)
